[
  {
    "slug": "rural-women-empowerment",
    "title": "Rural Women Empowerment Through Skill Training",
    "excerpt": "How women in villages are transforming their lives through skill development.",
    "image": "https://via.placeholder.com/800x500",
    "date": "2024-10-10",
    "content": "Full blog content goes here..."
  },
  {
    "slug": "organic-farming-success",
    "title": "Success Stories in Organic Farming",
    "excerpt": "Farmers embracing sustainable organic farming techniques.",
    "image": "https://via.placeholder.com/800x500",
    "date": "2024-11-01",
    "content": "Full blog content goes here..."
  },
  {
    "slug": "self-help-groups",
    "title": "The Growth of Self-Help Groups in Punjab Villages",
    "excerpt": "How community-driven SHGs are driving rural progress.",
    "image": "https://via.placeholder.com/800x500",
    "date": "2024-07-25",
    "content": "Full blog content goes here..."
  }
]
